pydist_cli/__init__.py
pydist_cli/__main__.py
pydist_cli/install.py
pydist_cli/publish.py
pydist_cli/settings.py
pydist_cli-0.1.1.dist-info/METADATA
pydist_cli-0.1.1.dist-info/WHEEL
pydist_cli-0.1.1.dist-info/entry_points.txt
pydist_cli-0.1.1.dist-info/top_level.txt
pydist_cli-0.1.1.dist-info/RECORD
