Metadata-Version: 2.1
Name: pydist-cli
Version: 0.1.1
Summary: CLI for uploading and downloading Python packages from pydist.com.
Home-page: https://github.com/alexbecker/pydist-cli
Author: Alex Becker
Author-email: alex@pydist.com
License: MIT
Keywords: packaging dependencies
Platform: UNKNOWN
Classifier: Development Status :: 3 - Alpha
Classifier: Intended Audience :: Developers
Classifier: License :: OSI Approved :: MIT License
Classifier: Programming Language :: Python
Classifier: Programming Language :: Python :: 3
Requires-Python: >=3.5
Requires-Dist: pip (>=10.0)
Requires-Dist: setuptools (>=39.0)
Requires-Dist: wheel
Requires-Dist: twine
